odoo/addons/ssi_fixed_asset_useful_life_estimation_change/README.rst
odoo/addons/ssi_fixed_asset_useful_life_estimation_change/__init__.py
odoo/addons/ssi_fixed_asset_useful_life_estimation_change/__manifest__.py
odoo/addons/ssi_fixed_asset_useful_life_estimation_change/data/approval_template_data.xml
odoo/addons/ssi_fixed_asset_useful_life_estimation_change/data/fixed_asset_depreciation_line_subtype_data.xml
odoo/addons/ssi_fixed_asset_useful_life_estimation_change/data/ir_sequence_data.xml
odoo/addons/ssi_fixed_asset_useful_life_estimation_change/data/policy_template_data.xml
odoo/addons/ssi_fixed_asset_useful_life_estimation_change/data/sequence_template_data.xml
odoo/addons/ssi_fixed_asset_useful_life_estimation_change/i18n/id.po
odoo/addons/ssi_fixed_asset_useful_life_estimation_change/i18n/ssi_fixed_asset_useful_life_estimation_change.pot
odoo/addons/ssi_fixed_asset_useful_life_estimation_change/models/__init__.py
odoo/addons/ssi_fixed_asset_useful_life_estimation_change/models/fixed_asset_useful_life_estimation_change.py
odoo/addons/ssi_fixed_asset_useful_life_estimation_change/security/ir.model.access.csv
odoo/addons/ssi_fixed_asset_useful_life_estimation_change/security/ir_module_category_data.xml
odoo/addons/ssi_fixed_asset_useful_life_estimation_change/security/ir_rule_data.xml
odoo/addons/ssi_fixed_asset_useful_life_estimation_change/security/res_group_data.xml
odoo/addons/ssi_fixed_asset_useful_life_estimation_change/static/description/banner.png
odoo/addons/ssi_fixed_asset_useful_life_estimation_change/static/description/icon.png
odoo/addons/ssi_fixed_asset_useful_life_estimation_change/views/fixed_asset_useful_life_estimation_change_view.xml
odoo14_addon_ssi_fixed_asset_useful_life_estimation_change-14.0.1.3.0.dist-info/METADATA
odoo14_addon_ssi_fixed_asset_useful_life_estimation_change-14.0.1.3.0.dist-info/WHEEL
odoo14_addon_ssi_fixed_asset_useful_life_estimation_change-14.0.1.3.0.dist-info/top_level.txt
odoo14_addon_ssi_fixed_asset_useful_life_estimation_change-14.0.1.3.0.dist-info/RECORD
